statsanalyzer/__init__.py
statsanalyzer/stats.py
statsanalyzer-0.1.0.dist-info/licenses/LICENSE
statsanalyzer-0.1.0.dist-info/METADATA
statsanalyzer-0.1.0.dist-info/WHEEL
statsanalyzer-0.1.0.dist-info/top_level.txt
statsanalyzer-0.1.0.dist-info/RECORD
