Metadata-Version: 2.4
Name: StatsAnalyzer
Version: 0.1.0
Summary: Perform advanced statistical analysis on numerical data
Author: ola al_qbita
Author-email: ola al_qbita <ola784377022@gmail.com>
License: 8MIT License
Project-URL: Homepage, https://pypi.org/project/StatsAnalyzer/
Requires-Python: >=3.13
License-File: LICENSE
Dynamic: author
Dynamic: license-file
Dynamic: requires-python
